tsqlike/__about__.py
tsqlike/__init__.py
tsqlike/tsqlike.py
tsqlike-1.1.8.dist-info/METADATA
tsqlike-1.1.8.dist-info/WHEEL
tsqlike-1.1.8.dist-info/licenses/LICENSE
tsqlike-1.1.8.dist-info/RECORD
