Metadata-Version: 2.3
Name: tSQLike
Version: 1.1.8
Summary: SQL-like interface to tabular structured data
Project-URL: Homepage, https://github.com/mezantrop/tSQLike
Project-URL: Issues, https://github.com/mezantrop/tSQLike/issues
Author-email: "<Mikhail Zakharov>" <zmey20000@yahoo.com>
License-File: LICENSE
Classifier: Intended Audience :: Developers
Classifier: Intended Audience :: Information Technology
Classifier: License :: OSI Approved :: BSD License
Classifier: Operating System :: OS Independent
Classifier: Programming Language :: Python :: 3
Classifier: Topic :: Database
Classifier: Topic :: File Formats
Classifier: Topic :: Scientific/Engineering :: Information Analysis
Classifier: Topic :: Software Development :: Libraries :: Python Modules
Requires-Python: >=3.8
Requires-Dist: tssplit>=1.0.7
